{
  "core": {
    "workingDir": ".reg",
    "actualDir": "e2e/screenshots",
    "thresholdRate": 0.001
  },
  "plugins": {
    "reg-simple-keygen-plugin": {
      "expectedKey": "${EXPECTED_KEY}",
      "actualKey": "${ACTUAL_KEY}"
    },
    "reg-publish-gcs-plugin": {
      "bucketName": "vrt-sample"
    },
    "reg-notify-github-plugin": {
      "clientId": "BcFRCsAgCADQE4U2tdFx/JA1tigyYcffexkrY6GTGeybI3U132sk1z5fgyoFSVDA44oVWx9t6u1O+SD+AQ==",
      "prComment": true,
      "prCommentBehavior": "default",
      "setCommitStatus": true,
      "shortDescription": false
    }
  }
}
